pageplanner/__init__.py
pageplanner/api.py
pageplanner/config.py
pageplanner/pageplanner.py
pageplanner/models/__init__.py
pageplanner/models/document.py
pageplanner/parsers/__init__.py
pageplanner/parsers/html_parser.py
pageplanner/parsers/text_normalizer.py
pageplanner/scraper/__init__.py
pageplanner/scraper/exceptions.py
pageplanner/scraper/scraper.py
pageplanner_benjihughes-0.22.dist-info/LICENSE
pageplanner_benjihughes-0.22.dist-info/METADATA
pageplanner_benjihughes-0.22.dist-info/WHEEL
pageplanner_benjihughes-0.22.dist-info/top_level.txt
pageplanner_benjihughes-0.22.dist-info/RECORD
