Metadata-Version: 2.1
Name: pageplanner-benjihughes
Version: 0.22
Summary: Scrapes URLs to create json documents with keyword counts by element.
Home-page: UNKNOWN
Author: Benji Hughes
License: MIT
Platform: UNKNOWN
Classifier: License :: OSI Approved :: MIT License
Classifier: Programming Language :: Python
Classifier: Programming Language :: Python :: 3
Classifier: Programming Language :: Python :: 3.6
Classifier: Programming Language :: Python :: Implementation :: CPython
Classifier: Programming Language :: Python :: Implementation :: PyPy
Requires-Python: >=3.6.0
Requires-Dist: requests
Requires-Dist: nltk
Requires-Dist: argparse
Requires-Dist: requests-html
Requires-Dist: lxml
Requires-Dist: urllib3
Requires-Dist: beautifulsoup4
